fm91/__init__.py
fm91/main.py
fm91-0.0.18.dist-info/entry_points.txt
fm91-0.0.18.dist-info/METADATA
fm91-0.0.18.dist-info/WHEEL
fm91-0.0.18.dist-info/RECORD
