Metadata-Version: 2.1
Name: fm91
Version: 0.0.18
Summary: A simple fastapi manager
Author: abirmunna
Author-email: mtmunna82@gmail.com
Requires-Python: >=3.10,<4.0
Classifier: Programming Language :: Python :: 3
Classifier: Programming Language :: Python :: 3.10
Classifier: Programming Language :: Python :: 3.11
Requires-Dist: python-dotenv (>=1.0.0,<2.0.0)
Requires-Dist: typer[all] (>=0.9.0,<0.10.0)
